src/twits.py
twitterAPI_sentiment-0.1.0.dist-info/METADATA
twitterAPI_sentiment-0.1.0.dist-info/WHEEL
twitterAPI_sentiment-0.1.0.dist-info/top_level.txt
twitterAPI_sentiment-0.1.0.dist-info/RECORD
