Metadata-Version: 2.1
Name: twitterAPI-sentiment
Version: 0.1.0
Summary: Analyzes the sentiment of tweets about any topic
Author: Aleksandr
Author-email: novacyan545@gmail.com
Requires-Dist: tweepy
Requires-Dist: textblob
